odoo/addons/sm_partago_usage/__init__.py
odoo/addons/sm_partago_usage/__manifest__.py
odoo/addons/sm_partago_usage/models/__init__.py
odoo/addons/sm_partago_usage/models/models_sm_company.py
odoo/addons/sm_partago_usage/models/models_sm_res_config_settings.py
odoo/addons/sm_partago_usage/models/models_smp_edit_reservation_compute_wizard.py
odoo/addons/sm_partago_usage/models/models_smp_reservation_compute.py
odoo/addons/sm_partago_usage/models/models_smp_reservation_wizard.py
odoo/addons/sm_partago_usage/models/models_smp_usage_cron.py
odoo/addons/sm_partago_usage/security/ir.model.access.csv
odoo/addons/sm_partago_usage/views/views.xml
odoo/addons/sm_partago_usage/views/views_cron.xml
odoo/addons/sm_partago_usage/views/views_edit_reservation_compute_wizard.xml
odoo/addons/sm_partago_usage/views/views_res_config_settings.xml
odoo/addons/sm_partago_usage/views/views_reservation_compute.xml
odoo/addons/sm_partago_usage/views/views_wizards.xml
odoo11_addon_sm_partago_usage-11.0.0.0.2.dist-info/METADATA
odoo11_addon_sm_partago_usage-11.0.0.0.2.dist-info/WHEEL
odoo11_addon_sm_partago_usage-11.0.0.0.2.dist-info/top_level.txt
odoo11_addon_sm_partago_usage-11.0.0.0.2.dist-info/RECORD
